sieve/__init__.py
sieve/sdk/__init__.py
sieve/sdk/config.py
sieve/sdk/exceptions.py
sieve/sdk/json_utils.py
sieve/sdk/apis/__init__.py
sieve/sdk/apis/base.py
sieve/sdk/collections/__init__.py
sieve/sdk/collections/document.py
sieve/sdk/sessions/__init__.py
sieve/sdk/sessions/base.py
sieve/sdk/sessions/proxied.py
sieve/sdk/sessions/semaphored.py
tests/test_collections/__init__.py
tests/test_collections/test_document.py
sieve_sdk-0.3.5.dist-info/METADATA
sieve_sdk-0.3.5.dist-info/WHEEL
sieve_sdk-0.3.5.dist-info/top_level.txt
sieve_sdk-0.3.5.dist-info/RECORD
