Metadata-Version: 2.1
Name: sieve-sdk
Version: 0.3.5
Summary: Sieve SDK
Home-page: https://bitbucket.org/sievetech/sieve-python-sdk
Author: Diogo Magalhaes Martins
Author-email: diogo.martins@sieve.com.br
License: UNKNOWN
Platform: UNKNOWN
Requires-Dist: aiodns (==1.1.1)
Requires-Dist: aiohttp (>=3.1.2)
Requires-Dist: aiologger (>=0.2.3)
Requires-Dist: aiosocksy (==0.1.2)
Requires-Dist: cchardet (==2.1.1)
Requires-Dist: pathdict (>=0.0.9)
